datalakesdk/__init__.py
datalakesdk/sdk.py
datalakesdk/types.py
datalakesdk/util.py
datalakesdk-0.0.8.dist-info/METADATA
datalakesdk-0.0.8.dist-info/WHEEL
datalakesdk-0.0.8.dist-info/top_level.txt
datalakesdk-0.0.8.dist-info/RECORD
