Metadata-Version: 2.1
Name: datalakesdk
Version: 0.0.8
Summary: DataLake SDK
Home-page: UNKNOWN
Author: ivan
Author-email: ivan.liu@anker-in.com
License: MIT License
Platform: UNKNOWN
Requires-Dist: hachoir (==3.3.0)
Requires-Dist: httpx (==0.27.1)
Requires-Dist: pydantic (==2.9.2)
Requires-Dist: requests (==2.31.0)
